setup.py
anime1_dl.egg-info/PKG-INFO
anime1_dl.egg-info/SOURCES.txt
anime1_dl.egg-info/dependency_links.txt
anime1_dl.egg-info/entry_points.txt
anime1_dl.egg-info/top_level.txt
anime1dl/__main__.py