Metadata-Version: 1.1
Name: anime1-dl
Version: 1.0.20
Summary: A simple downloader for http://www.anime1.com
Home-page: https://github.com/Dragneel1234
Author: Dragneel1234
Author-email: blwal7057@gmail.com
License: MPL-2.0
Platform: UNKNOWN
Classifier: Environment :: Console
Classifier: Topic :: Utilities
